nytxw_puz/decompress.py
nytxw_puz/main.py
nytxw_puz/puz.py
utils/nytxw_gen.py
nytxw_puz_cli-1.1.0.dist-info/entry_points.txt
nytxw_puz_cli-1.1.0.dist-info/LICENSE
nytxw_puz_cli-1.1.0.dist-info/WHEEL
nytxw_puz_cli-1.1.0.dist-info/METADATA
nytxw_puz_cli-1.1.0.dist-info/RECORD
