Metadata-Version: 2.1
Name: nytxw-puz-cli
Version: 1.1.0
Summary: CLI tool to convert NY Times crosswords into Across Lite files (.puz)
Home-page: https://github.com/GodTamIt/nytxw-puz-cli
License: BSD-2-Clause
Author: Chris Tam
Author-email: ohgodtamit@gmail.com
Requires-Python: >=3.7,<4.0
Classifier: License :: OSI Approved :: BSD License
Classifier: Programming Language :: Python :: 3
Classifier: Programming Language :: Python :: 3.10
Classifier: Programming Language :: Python :: 3.7
Classifier: Programming Language :: Python :: 3.8
Classifier: Programming Language :: Python :: 3.9
Requires-Dist: colorlog (>=6.6.0,<7.0.0)
Requires-Dist: pendulum (>=2.1.2,<3.0.0)
Requires-Dist: requests (>=2.26.0,<3.0.0)
Project-URL: Repository, https://github.com/GodTamIt/nytxw-puz-cli
